vayaAuto/__init__.py
vayaAuto/option.py
vayaAuto/section.py
vayaAuto/utils.py
vayaAuto/vayadrive.py
vayaAuto/configurations/__init__.py
vayaAuto/configurations/vayadrive_params.yaml
vayaAuto-0.0.7.dist-info/METADATA
vayaAuto-0.0.7.dist-info/WHEEL
vayaAuto-0.0.7.dist-info/top_level.txt
vayaAuto-0.0.7.dist-info/RECORD
