Metadata-Version: 2.1
Name: vayaAuto
Version: 0.0.7
Summary: UNKNOWN
Home-page: UNKNOWN
Author: System and Application team
Author-email: Dor.Mesilati@leddartech.com
License: UNKNOWN
Platform: UNKNOWN
Classifier: Programming Language :: Python :: 3
Classifier: License :: OSI Approved :: MIT License
Classifier: Operating System :: OS Independent
Requires-Python: >=3.6
Requires-Dist: PyYaml
